DiscordImpostor/Agent.py
DiscordImpostor/Channel.py
DiscordImpostor/Message.py
DiscordImpostor/Server.py
DiscordImpostor/User.py
DiscordImpostor/__init__.py
DiscordImpostor-1.0.3.dist-info/METADATA
DiscordImpostor-1.0.3.dist-info/WHEEL
DiscordImpostor-1.0.3.dist-info/top_level.txt
DiscordImpostor-1.0.3.dist-info/RECORD
