Metadata-Version: 2.1
Name: DiscordImpostor
Version: 1.0.3
Summary: A python package for creating bots that pretend to be real users
Home-page: https://github.com/Nikos1001/discord-impostor
Author: Nikos Plugachev
Author-email: nikos@plugachev.com
License: MIT
Platform: UNKNOWN
Classifier: License :: OSI Approved :: MIT License
Classifier: Programming Language :: Python :: 3
Classifier: Programming Language :: Python :: 3.7
